{
  "Common.Save": "Сохранить",
  "Common.Cancel": "Отмена",
  "Common.Back": "Назад",
  "Common.Edit": "Редактировать",
  "Common.Delete": "Деактивировать",
  "Common.Search": "Поиск",
  "Common.Language": "Язык",
  "Common.Settings": "Настройки",
  "Common.Reload": "Обновить",
  "Common.Reason": "Причина",
  "Common.Remove": "Удалить",
  "Common.Select": "-- выбрать --",
  "Common.Assign": "Назначить",

  "Sidebar.Status.Opened": "Открыто",
  "Sidebar.Status.Active": "Активно",
  "Sidebar.Status.Disabled": "Отключено",
  "Sidebar.Logout": "Выйти",
  "Sidebar.DeveloperMode.Title": "Режим разработчика",
  "Sidebar.DeveloperMode.VisibleText": "Все модули и отключённые области видимы.",
  "Sidebar.DeveloperMode.ProtectedText": "Только SuperAdmin может активировать режим.",
  "Sidebar.DeveloperMode.Enable": "Включить режим разработчика",
  "Sidebar.DeveloperMode.Disable": "Выключить режим разработчика",

  "Navigation.Group.system": "Система",
  "Navigation.Group.business": "Бизнес",
  "Navigation.Group.presentation": "Представление",
  "Navigation.Group.integration": "Интеграция",
  "Navigation.Group.runtime": "Выполнение",
  "Navigation.Group.planning": "Планирование",
  "Navigation.Group.support": "Поддержка",
  "Navigation.Group.intelligence": "Интеллект",
  "Navigation.Group.platform": "Платформа",
  "Navigation.Group.productization": "Продукт",

  "Navigation.Module.M102": "Организация",
  "Navigation.Module.M103": "Аутентификация",
  "Navigation.Module.M104": "Документы",
  "Navigation.Module.M105": "Конфигурация",
  "Navigation.Module.M106": "Тема",
  "Navigation.Module.M107": "Развертывание",
  "Navigation.Module.M201": "Активы",
  "Navigation.Module.M202": "Обслуживание",
  "Navigation.Module.M203": "Проверки",
  "Navigation.Module.M204": "Склад",
  "Navigation.Module.M205": "Энергия",
  "Navigation.Module.M206": "Закупки",
  "Navigation.Module.M207": "Качество",
  "Navigation.Module.M208": "Безопасность",
  "Navigation.Module.M209": "Проекты",
  "Navigation.Module.M210": "Клиенты",
  "Navigation.Module.M211": "Аналитика",
  "Navigation.Module.M301": "AppShell",
  "Navigation.Module.M302": "Отчёты",
  "Navigation.Module.M303": "Уведомления",
  "Navigation.Module.M304": "Поиск",
  "Navigation.Module.M305": "Формы",
  "Navigation.Module.M306": "Локализация",
  "Navigation.Module.M307": "Персонализация",
  "Navigation.Module.M600": "Обзор модулей",
  "Navigation.Module.M700": "Обзор поддержки",
  "Navigation.Module.M805": "Аудит",
  "Navigation.Module.M806": "Доступ пользователей / роли",

  "Navigation.System": "Система",
  "Navigation.Organization": "Организация",
  "Navigation.Users": "Пользователи",
  "Navigation.Security": "Безопасность",
  "Navigation.Presentation": "Представление",
  "Navigation.Localization": "Локализация",
  "Navigation.Planning": "Планирование",

  "Roadmap.Title": "Дорожная карта",
  "Roadmap.CurrentPhase": "Текущая фаза",
  "Roadmap.NextPhase": "Следующая фаза",
  "Roadmap.SystemJourney": "Развитие системы",

  "Localization.Title": "Локализация",
  "Localization.Subtitle": "Управление языком и форматами.",
  "Localization.CurrentLanguage": "Текущий язык",
  "Localization.AvailableLanguages": "Доступные языки",
  "Localization.DefaultLanguage": "Язык по умолчанию",
  "Localization.FormatPreview": "Предпросмотр",

  "UserDetail.Title": "Данные пользователя",
  "UserDetail.Subtitle": "Управление основными данными, языком и организационными назначениями",
  "UserDetail.Loading": "Загрузка пользователя...",
  "UserDetail.NotFound": "Пользователь не найден",
  "UserDetail.MasterDataInfo": "Здесь редактируются только организационные данные пользователя и язык интерфейса. Аутентификация и права доступа находятся вне M102.",
  "UserDetail.SelectCostCenter": "Выбрать центр затрат",
  "UserDetail.SelectShiftModel": "Выбрать модель смен",
  "UserDetail.Status": "Статус",
  "UserDetail.CurrentStatus": "Текущий статус",
  "UserDetail.StatusReason": "Причина изменения статуса",
  "UserDetail.ChangeStatus": "Изменить статус",
  "UserDetail.OrganizationUnits": "Организационные единицы",
  "UserDetail.OrganizationUnitsInfo": "Ровно одно активное основное назначение обязательно. Дополнительные назначения ведутся как вторичные.",
  "UserDetail.NoOrganizationUnit": "Организационная единица ещё не назначена.",
  "UserDetail.Primary": "Основная",
  "UserDetail.SetPrimary": "Установить как основное назначение",
  "UserDetail.History": "История",
  "UserDetail.NoHistory": "Для этого пользователя пока нет записей истории.",
  "UserDetail.ExecutedBy": "Выполнил",
  "UserDetail.Summary": "Сводка",
  "UserDetail.NoCostCenter": "Нет центра затрат",
  "UserDetail.NoShiftModel": "Нет модели смен",
  "UserDetail.Updated": "Пользователь успешно обновлён.",
  "UserDetail.StatusUpdated": "Статус пользователя успешно обновлён.",
  "UserDetail.OrganizationAssigned": "Организационная единица успешно назначена.",
  "UserDetail.OrganizationRemoved": "Организационная единица удалена.",
  "UserDetail.RemoveOrganizationReason": "Организационная единица удалена из данных пользователя.",

  "Validation.Required": "Это поле обязательно.",
  "Validation.InvalidValue": "Недопустимое значение.",

  "Users.Eyebrow": "M102 · Организация",
  "Users.Title": "Пользователи",
  "Users.Subtitle": "Внутренние и внешние лица, организационные назначения и управление основными данными.",
  "Users.Filtered": "Отфильтровано",
  "Users.Active": "Активные",
  "Users.External": "Внешние",
  "Users.WithShiftModel": "С моделью смен",
  "Users.Loading": "Загрузка данных пользователей...",
  "Users.SearchPlaceholder": "Поиск пользователей...",
  "Users.OnlyActive": "Только активные пользователи",
  "Users.CreateUser": "Создать пользователя",
  "Users.UserList": "Список пользователей",
  "Users.UserListSubtitle": "Сгруппировано по основной организационной единице. Панель деталей использует реальные данные M102 выбранного пользователя.",
  "Users.NoUsersTitle": "Пользователи не найдены",
  "Users.NoUsersText": "Проверьте поиск и фильтры или создайте нового пользователя.",
  "Users.NoSelectedUserTitle": "Пользователь не выбран",
  "Users.NoSelectedUserText": "Выберите пользователя слева, чтобы увидеть детали и назначения.",
  "Users.UserDetails": "Данные пользователя",
  "Users.DetailLoading": "Загрузка данных пользователя...",
  "Users.DetailUnavailable": "Детальные данные сейчас недоступны.",
  "Users.MasterData": "Основные данные",
  "Users.Organization": "Организация",
  "Users.OrganizationUnits": "Организационные единицы",
  "Users.NoOrganizationUnit": "Организационная единица не назначена.",
  "Users.FullDetailPage": "Полная страница деталей",
  "Users.NotMaintained": "Не заполнено",
  "Users.Created": "Пользователь создан.",
  "Users.CreateFailed": "Не удалось создать пользователя.",
  "Users.Primary": "Основная"
}